tklpy/__init__.py
tklpy/tkl.py
tklpy/utils.py
tklpy-0.0.1.dist-info/LICENSE.txt
tklpy-0.0.1.dist-info/METADATA
tklpy-0.0.1.dist-info/WHEEL
tklpy-0.0.1.dist-info/top_level.txt
tklpy-0.0.1.dist-info/RECORD
