Metadata-Version: 2.1
Name: tklpy
Version: 0.0.1
Summary: Python implementation of the Transfer Kernel Learning method developed by Long et. al. (2015).
Home-page: http://github.com/jrjoaorenato/tklpy
Author: João Renato Ribeiro Manesco
Author-email: joaorenatorm@gmail.com
License: MIT
Download-URL: https://github.com/jrjoaorenato/tklpy/archive/0.0.1.tar.gz
Keywords: Domain Adaptation,Machine Learning,TKL,Domain Invariant Transfer Kernel Learning
Platform: UNKNOWN
Classifier: Development Status :: 3 - Alpha
Classifier: Intended Audience :: Developers
Classifier: Topic :: Software Development :: Build Tools
Classifier: License :: OSI Approved :: MIT License
Classifier: Programming Language :: Python :: 3
Classifier: Programming Language :: Python :: 3.8
Requires-Dist: numpy
Requires-Dist: qpsolvers
Requires-Dist: quadprog
Requires-Dist: scikit-learn
Requires-Dist: scipy
